[
    {
        "name": "An Nguyen",
        "id": "100000036363883"
    },
    {
        "name": "Leonardo Jose Rojas Vasquez",
        "id": "100000297164675"
    },
    {
        "name": "Cong Nguyenvan",
        "id": "100007738353328"
    },
    {
        "name": "Phuoc Do",
        "id": "100008392478448"
    },
    {
        "name": "Ameen Alqorari",
        "id": "100008626326969"
    },
    {
        "name": "Abu Habib",
        "id": "100009852796129"
    },
    {
        "name": "nguyễn Tôn",
        "id": "100010296640495"
    },
    {
        "name": "Quang Dũng",
        "id": "100010857348749"
    },
    {
        "name": "Không Co Chủ",
        "id": "100013310552330"
    },
    {
        "name": "Thúy Ngô Minh",
        "id": "100013385653325"
    },
    {
        "name": "P O Fp",
        "id": "100013394461912"
    },
    {
        "name": "Åbđű ŁŁăh",
        "id": "100014716953013"
    },
    {
        "name": "Phungcao Phungcao",
        "id": "100014768530694"
    },
    {
        "name": "Nguyen ÐôngPhuong",
        "id": "100015522131200"
    },
    {
        "name": "Nobi Ta",
        "id": "100016670538243"
    },
    {
        "name": "Dân Quẩy",
        "id": "100018412811176"
    },
    {
        "name": "Trần Thị Huyền Trang",
        "id": "100023186555866"
    },
    {
        "name": "Bach Tuyet",
        "id": "100024433894607"
    },
    {
        "name": "ذالنون احمد غيلان",
        "id": "100024603397735"
    },
    {
        "name": "Ken's Bi",
        "id": "100025095821881"
    },
    {
        "name": "Hong Hien",
        "id": "100025347786527"
    },
    {
        "name": "Vi Khánh",
        "id": "100025713395670"
    },
    {
        "name": "Minh Anh",
        "id": "100026174805227"
    },
    {
        "name": "Bi Bi",
        "id": "100026698687242"
    },
    {
        "name": "Zagim Ali",
        "id": "100027783617812"
    },
    {
        "name": "Pé Tủn",
        "id": "100028444924509"
    },
    {
        "name": "Amir Zall",
        "id": "100028587460543"
    },
    {
        "name": "Hắc Vũ Thần",
        "id": "100029142847562"
    },
    {
        "name": "Osvaldo Camejo",
        "id": "100029281663396"
    },
    {
        "name": "Heo Lầyy",
        "id": "100029335222409"
    },
    {
        "name": "Tinh Siu",
        "id": "100029995040313"
    },
    {
        "name": "Trần Thị Minh Nhung",
        "id": "100030046957522"
    },
    {
        "name": "Trần Mẫnn",
        "id": "100030211247994"
    },
    {
        "name": "Cảnh Ann",
        "id": "100030246197183"
    },
    {
        "name": "Md Ashif Alam",
        "id": "100030851799972"
    },
    {
        "name": "Kevin Syaputra",
        "id": "100031724053312"
    },
    {
        "name": "Trang Trang",
        "id": "100033259681476"
    },
    {
        "name": "Khôi Đag Bõ Rưởu",
        "id": "100033364512617"
    },
    {
        "name": "Duong Anh",
        "id": "100033427621792"
    },
    {
        "name": "Doanh Phù Dung",
        "id": "100034041764035"
    },
    {
        "name": "Nguyễn Minh Hiếu",
        "id": "100034612144171"
    },
    {
        "name": "Đang Ngọc Vân",
        "id": "100034626997619"
    },
    {
        "name": "Mien Tay Yeu Thuong",
        "id": "100034971888701"
    },
    {
        "name": "Hạ Con Bà Loan",
        "id": "100035009101703"
    },
    {
        "name": "Bé Oanh",
        "id": "100035194532140"
    },
    {
        "name": "Prince Agbaje Akinjide",
        "id": "100035908279956"
    },
    {
        "name": "Zwe Thura",
        "id": "100036073277485"
    },
    {
        "name": "Tịnh Vi",
        "id": "100036141660122"
    },
    {
        "name": "Đen Nhỏ",
        "id": "100036873017127"
    },
    {
        "name": "Pé Kiểng",
        "id": "100037054002824"
    },
    {
        "name": "Du Nguyễn",
        "id": "100037258110967"
    },
    {
        "name": "محمد امين القراري القراري",
        "id": "100037332590570"
    },
    {
        "name": "Tuấn Minh Trần",
        "id": "100037453689000"
    },
    {
        "name": "Hân Trần",
        "id": "100037505177040"
    },
    {
        "name": "Tú Bảnh Vinahouse",
        "id": "100037626194108"
    },
    {
        "name": "Trang Nguyễn",
        "id": "100037747878122"
    },
    {
        "name": "Lê Toàn",
        "id": "100037805830288"
    },
    {
        "name": "Huỳnh Y's",
        "id": "100038141693791"
    },
    {
        "name": "Star Love Hannah",
        "id": "100038611330660"
    },
    {
        "name": "Phạm Phương",
        "id": "100038943005067"
    },
    {
        "name": "Ông Trời Con",
        "id": "100039148522386"
    },
    {
        "name": "Thầy Yoongi",
        "id": "100039543942894"
    },
    {
        "name": "Hùng Sói",
        "id": "100039780559732"
    },
    {
        "name": "Đức Hòa",
        "id": "100039897852238"
    },
    {
        "name": "Tub Poob Zoo",
        "id": "100039951666662"
    },
    {
        "name": "Nguyễn PHú Hoài",
        "id": "100039957936293"
    },
    {
        "name": "Ngư Song",
        "id": "100040182305423"
    },
    {
        "name": "Chí Phèo",
        "id": "100040341048006"
    },
    {
        "name": "Ly Nè",
        "id": "100040492039718"
    },
    {
        "name": "Tho Danh",
        "id": "100040575183355"
    },
    {
        "name": "مجدي شحم",
        "id": "100040596350376"
    },
    {
        "name": "An Huynh",
        "id": "100040606231268"
    },
    {
        "name": "Hạ Băng",
        "id": "100040891234885"
    },
    {
        "name": "Ýy Nhii",
        "id": "100040933629714"
    },
    {
        "name": "Nguyễn Trân",
        "id": "100041035371748"
    },
    {
        "name": "Thích Là Nhích",
        "id": "100041077350178"
    },
    {
        "name": "Gấu Bắc Cực",
        "id": "100041102737789"
    },
    {
        "name": "Huyền Đang Đi Bay",
        "id": "100041196870020"
    },
    {
        "name": "Thanh Nhã",
        "id": "100041196909642"
    },
    {
        "name": "Zin",
        "id": "100041199070729"
    },
    {
        "name": "Khu Som Chua",
        "id": "100041224200518"
    },
    {
        "name": "Lan Nhi",
        "id": "100041297949638"
    },
    {
        "name": "Ngô Minh Thuỳ",
        "id": "100041337858940"
    },
    {
        "name": "Xuân Thành",
        "id": "100041376481396"
    },
    {
        "name": "Nguyễn Thị Tuyết Nhung",
        "id": "100041407371537"
    },
    {
        "name": "Hànn Mẫnn Nhii",
        "id": "100041500713708"
    },
    {
        "name": "Trần Văn Trí",
        "id": "100041523645226"
    },
    {
        "name": "Vàng Văn",
        "id": "100041538696742"
    },
    {
        "name": "Hk Co Tên",
        "id": "100041584013184"
    },
    {
        "name": "Trúc Trúc",
        "id": "100041615362710"
    },
    {
        "name": "Raja Wadon Brazagan",
        "id": "100041665146048"
    },
    {
        "name": "Hùynh Kim Phượng",
        "id": "100041694036130"
    },
    {
        "name": "Tuấn Toàn",
        "id": "100041720543011"
    },
    {
        "name": "Nguyễn Thanh Huy",
        "id": "100041723661646"
    },
    {
        "name": "Giang Hương Vũ",
        "id": "100041733902531"
    },
    {
        "name": "Ngân Lạc",
        "id": "100042005430034"
    },
    {
        "name": "Thị Tuyết Trang",
        "id": "100042080781238"
    },
    {
        "name": "Phùng Mai Phương",
        "id": "100042371839323"
    },
    {
        "name": "LụC LaM",
        "id": "100042407627255"
    },
    {
        "name": "Vy Deptry",
        "id": "100042426619535"
    },
    {
        "name": "孟祥辉",
        "id": "100042428536102"
    },
    {
        "name": "Kiều My",
        "id": "100042463056156"
    },
    {
        "name": "Lan Mai",
        "id": "100042710326299"
    },
    {
        "name": "Phuc Le",
        "id": "100042717982384"
    },
    {
        "name": "Ha Lê Sun",
        "id": "100042764059630"
    },
    {
        "name": "Bạch Nhã Thiên",
        "id": "100042775513828"
    },
    {
        "name": "Thư Thư",
        "id": "100042912075842"
    },
    {
        "name": "Em Nhi",
        "id": "100042918066512"
    },
    {
        "name": "နွလံုးသား ရဲ႕ သံေယာဇဥ္",
        "id": "100043038587047"
    },
    {
        "name": "Kudo Shinichi",
        "id": "100043090908609"
    },
    {
        "name": "Kim Thiên",
        "id": "100043210577192"
    },
    {
        "name": "Thảo Mai",
        "id": "100043213104030"
    },
    {
        "name": "Jikun Kim",
        "id": "100043214242532"
    },
    {
        "name": "Bắp Cải",
        "id": "100043292587915"
    },
    {
        "name": "Nhã Trâm",
        "id": "100043313448646"
    },
    {
        "name": "Thái Sự",
        "id": "100043369853533"
    },
    {
        "name": "Thiên'z Kim'z Lãnh'z Hoàng'z",
        "id": "100043438667872"
    },
    {
        "name": "Hau Nguyen",
        "id": "100043628303001"
    },
    {
        "name": "Muhammad Rio",
        "id": "100043725969237"
    },
    {
        "name": "Diloi Thang",
        "id": "100043730550272"
    },
    {
        "name": "Ko Chit",
        "id": "100043741013211"
    },
    {
        "name": "Hoan Lo",
        "id": "100043794288889"
    },
    {
        "name": "Na Lê",
        "id": "100043837690671"
    },
    {
        "name": "Gurjant Singh Gurjant",
        "id": "100043841231091"
    },
    {
        "name": "Nguyễn Thị Ngọc Ánh",
        "id": "100043867598876"
    },
    {
        "name": "Lâm Thúy",
        "id": "100043887904735"
    },
    {
        "name": "Nhi Vẫn Đi Học",
        "id": "100043930669041"
    },
    {
        "name": "Sahara Ara",
        "id": "100043942455601"
    },
    {
        "name": "Hau Le",
        "id": "100043952420886"
    },
    {
        "name": "Huyền Huyền",
        "id": "100043964316157"
    },
    {
        "name": "Thay Their Em Riêng",
        "id": "100044017993434"
    },
    {
        "name": "Bro Sea Thai",
        "id": "100044030223958"
    },
    {
        "name": "Pé's Pé's",
        "id": "100044094735886"
    },
    {
        "name": "Trần Dương",
        "id": "100044109618308"
    },
    {
        "name": "Phương Thu",
        "id": "100044111871865"
    },
    {
        "name": "Abdul Sattr",
        "id": "100044154240114"
    },
    {
        "name": "Ko Shine",
        "id": "100044183663746"
    },
    {
        "name": "Gianqq Henry",
        "id": "100044220459536"
    },
    {
        "name": "Lan Nguyenvan",
        "id": "100044314144610"
    },
    {
        "name": "Đặng Quý",
        "id": "100044347371436"
    },
    {
        "name": "Ngô Huy Hoàng",
        "id": "100044399539254"
    },
    {
        "name": "Lãnh Hàn Thiên Di",
        "id": "100044410120087"
    },
    {
        "name": "Thi Vũ",
        "id": "100044428730559"
    },
    {
        "name": "Dai Lo",
        "id": "100044437220635"
    },
    {
        "name": "Bốc Bác Họ",
        "id": "100044465854996"
    },
    {
        "name": "Hoàng Thu Liễu",
        "id": "100044542604431"
    },
    {
        "name": "Anh Chi",
        "id": "100044556214895"
    },
    {
        "name": "Cường Lâm",
        "id": "100044561443057"
    },
    {
        "name": "Dô Han",
        "id": "100044642482612"
    },
    {
        "name": "Haruko Yusarino",
        "id": "100044663718656"
    },
    {
        "name": "Tắt Nguồn",
        "id": "100044693209127"
    },
    {
        "name": "Khuê Iris",
        "id": "100044713684332"
    },
    {
        "name": "Mộc Nhiên",
        "id": "100044717467342"
    },
    {
        "name": "Quốc Dảk",
        "id": "100044727528769"
    },
    {
        "name": "Vương Lạc Giai Kỳ",
        "id": "100044746341565"
    },
    {
        "name": "Đen Thui",
        "id": "100044757155778"
    },
    {
        "name": "Nazmul Hossen",
        "id": "100044774473048"
    },
    {
        "name": "Chi'ss Em'ss",
        "id": "100044788250247"
    },
    {
        "name": "Đậu Vinh",
        "id": "100044816461267"
    },
    {
        "name": "Đặng Khánh Giao",
        "id": "100044858721544"
    },
    {
        "name": "Ko Gyi",
        "id": "100044864329475"
    },
    {
        "name": "Thằng Khờ",
        "id": "100044878269259"
    },
    {
        "name": "Hồ Bảo Hà",
        "id": "100044897930139"
    },
    {
        "name": "Koko",
        "id": "100044903511519"
    },
    {
        "name": "Văn Lượm",
        "id": "100044905892521"
    },
    {
        "name": "Thiri Zaw",
        "id": "100044963749179"
    },
    {
        "name": "Tên Ko",
        "id": "100044966355736"
    },
    {
        "name": "Imam Khan",
        "id": "100044979823965"
    },
    {
        "name": "လိုအပ္သူ လိုအပ္သူ",
        "id": "100044988935263"
    },
    {
        "name": "Nghĩa Plus",
        "id": "100044990300198"
    },
    {
        "name": "Học Vũ",
        "id": "100045027093025"
    },
    {
        "name": "Trần Thanh An",
        "id": "100045039286551"
    },
    {
        "name": "Huynh Cutu Thao",
        "id": "100045058397614"
    },
    {
        "name": "Ngọc Hân",
        "id": "100045070865815"
    },
    {
        "name": "Brij Kishor Giri",
        "id": "100045073694421"
    },
    {
        "name": "Om Mani Padme Hum",
        "id": "100045099637701"
    },
    {
        "name": "Hưng Gờ",
        "id": "100045105102023"
    },
    {
        "name": "Interpreter's Cute's",
        "id": "100045140773906"
    },
    {
        "name": "Ánh Dương",
        "id": "100045207340943"
    },
    {
        "name": "Ngọc Thy",
        "id": "100045216279989"
    },
    {
        "name": "Karan Raj",
        "id": "100045279218213"
    },
    {
        "name": "Long Stus",
        "id": "100045312485940"
    },
    {
        "name": "Hải CoN",
        "id": "100045336515010"
    },
    {
        "name": "Hà Vũ",
        "id": "100045342516030"
    },
    {
        "name": "ေဇ ယ်",
        "id": "100045344162603"
    },
    {
        "name": "Hương Ly",
        "id": "100045347794669"
    },
    {
        "name": "Huỳnh Tú Tâm",
        "id": "100045353430468"
    },
    {
        "name": "Thiên Tâm",
        "id": "100045365853266"
    }
]