[
    {
        "name": "Khiareddine Romane",
        "id": "1218423466"
    },
    {
        "name": "მაკა თვაური",
        "id": "100000497359869"
    },
    {
        "name": "Poyou Franco",
        "id": "100000709995804"
    },
    {
        "name": "Antôn Hoàng Tuyên",
        "id": "100000991491879"
    },
    {
        "name": "Tân Nguyễn",
        "id": "100001281658154"
    },
    {
        "name": "Wong Yong",
        "id": "100001315082676"
    },
    {
        "name": "Steve Hoo",
        "id": "100002509982803"
    },
    {
        "name": "Quang Minh",
        "id": "100002690812053"
    },
    {
        "name": "Trương Thông",
        "id": "100002731321706"
    },
    {
        "name": "An Hòa Hữu",
        "id": "100003326816339"
    },
    {
        "name": "Thiên Ân",
        "id": "100003372765609"
    },
    {
        "name": "Cao Xiuxiu",
        "id": "100003602807659"
    },
    {
        "name": "Sika Asentewa Asiedua",
        "id": "100003630663532"
    },
    {
        "name": "Nguyễn Văn Chung",
        "id": "100003715210712"
    },
    {
        "name": "Nguyễn Trựzkk",
        "id": "100003764735978"
    },
    {
        "name": "Hien Nguyen",
        "id": "100003878182843"
    },
    {
        "name": "Trang Dang",
        "id": "100003885758927"
    },
    {
        "name": "Quỳnh Vân",
        "id": "100004036043548"
    },
    {
        "name": "Phạm Văn Thảo",
        "id": "100004174716606"
    },
    {
        "name": "Thương LV",
        "id": "100004197910557"
    },
    {
        "name": "Hoang Long",
        "id": "100004210962048"
    },
    {
        "name": "Hậu Phạm",
        "id": "100004452765720"
    },
    {
        "name": "Dũng Là Đà",
        "id": "100004552800904"
    },
    {
        "name": "Nguyên Hưu Thăng",
        "id": "100004566301163"
    },
    {
        "name": "Đặng Thanh Hùng",
        "id": "100004591204999"
    },
    {
        "name": "Thu Hà Yđ",
        "id": "100004637492453"
    },
    {
        "name": "Minh Tri",
        "id": "100004927119341"
    },
    {
        "name": "Lệ Thúy",
        "id": "100005024952918"
    },
    {
        "name": "Lê Đại Nhân",
        "id": "100005088964493"
    },
    {
        "name": "Thương Lee",
        "id": "100005169760738"
    },
    {
        "name": "Trình Tqt",
        "id": "100005338860314"
    },
    {
        "name": "Ti Ti",
        "id": "100005547109019"
    },
    {
        "name": "Thanh Lương",
        "id": "100005656173590"
    },
    {
        "name": "Thoại Lâm",
        "id": "100005723563600"
    },
    {
        "name": "Linh Lung Linh",
        "id": "100005788751606"
    },
    {
        "name": "Bảo Lộc",
        "id": "100005865245914"
    },
    {
        "name": "Nghĩa Nguyễn",
        "id": "100005926958062"
    },
    {
        "name": "Tuấn Vũ",
        "id": "100006499311619"
    },
    {
        "name": "bỉnh Pé út bướng",
        "id": "100006507649688"
    },
    {
        "name": "Trần Hùng",
        "id": "100006818192705"
    },
    {
        "name": "Phạm Long",
        "id": "100006885007671"
    },
    {
        "name": "Văn Trường",
        "id": "100006922367786"
    },
    {
        "name": "Xuan Lythi",
        "id": "100006987049234"
    },
    {
        "name": "Đoàn Đình Dương",
        "id": "100007072894592"
    },
    {
        "name": "Phạm Vũ",
        "id": "100007117092774"
    },
    {
        "name": "Mai Hương",
        "id": "100007210986045"
    },
    {
        "name": "Quang Thái",
        "id": "100007248187947"
    },
    {
        "name": "Thiên Phúc Nguyễn Hoàng",
        "id": "100007924782601"
    },
    {
        "name": "Hồng Lài",
        "id": "100007954812684"
    },
    {
        "name": "Minh Khánh",
        "id": "100007995106734"
    },
    {
        "name": "Van Nguyen",
        "id": "100007996513855"
    },
    {
        "name": "Sống Tự Nhiên",
        "id": "100008037226476"
    },
    {
        "name": "Tien Nguyen",
        "id": "100008055887712"
    },
    {
        "name": "Chử Đức Đại",
        "id": "100008067271640"
    },
    {
        "name": "Sửu Nhi",
        "id": "100008191381339"
    },
    {
        "name": "Nguyễn Văn Chính",
        "id": "100008260780714"
    },
    {
        "name": "Thonglanh Nguyen",
        "id": "100008337872019"
    },
    {
        "name": "Duy Lộc",
        "id": "100008417689385"
    },
    {
        "name": "Sala Tran",
        "id": "100008974625703"
    },
    {
        "name": "Phuc Nguyen",
        "id": "100009011305895"
    },
    {
        "name": "Anh Son",
        "id": "100009040864474"
    },
    {
        "name": "Tuấn nguyễn văn",
        "id": "100009079671183"
    },
    {
        "name": "Người Lạ Mạt",
        "id": "100009121945144"
    },
    {
        "name": "Xuanki Lê",
        "id": "100009234532917"
    },
    {
        "name": "Đào Thị Oanhh",
        "id": "100009253324221"
    },
    {
        "name": "Hưng Nguyễn",
        "id": "100009402044870"
    },
    {
        "name": "Tú Lee",
        "id": "100009469389390"
    },
    {
        "name": "Quynh Như Như",
        "id": "100009795018228"
    },
    {
        "name": "Lòng Người khó Đón",
        "id": "100009930159476"
    },
    {
        "name": "Tịnh Nguyễn",
        "id": "100010221480275"
    },
    {
        "name": "Dinh Nguyễn Trường",
        "id": "100010495051068"
    },
    {
        "name": "Trương Hung Anh",
        "id": "100010525273360"
    },
    {
        "name": "Trong Tran",
        "id": "100010636725253"
    },
    {
        "name": "Nhan Dương",
        "id": "100010689341244"
    },
    {
        "name": "Dee Dee",
        "id": "100011295245003"
    },
    {
        "name": "Ngọc Mai",
        "id": "100011613846656"
    },
    {
        "name": "RY Sam Sam",
        "id": "100012548071973"
    },
    {
        "name": "Quang Le",
        "id": "100012602923686"
    },
    {
        "name": "Anh Phuc Truong",
        "id": "100012658597843"
    },
    {
        "name": "Thanh Nguyen",
        "id": "100012744787589"
    },
    {
        "name": "Khoai To",
        "id": "100012898862513"
    },
    {
        "name": "Ngô Đào Việt Hùng",
        "id": "100013098432090"
    },
    {
        "name": "Nguyêên Nguyêên",
        "id": "100013126171226"
    },
    {
        "name": "Hoang Trung",
        "id": "100013336605716"
    },
    {
        "name": "Nguyên Phú",
        "id": "100013357023310"
    },
    {
        "name": "Phi Hùng",
        "id": "100013501441410"
    },
    {
        "name": "Yen Duong",
        "id": "100013553866686"
    },
    {
        "name": "Hoa Lê",
        "id": "100013672475102"
    },
    {
        "name": "Thái Thị Yến Ngọc",
        "id": "100014185350238"
    },
    {
        "name": "Nguyễn Duy",
        "id": "100014824270437"
    },
    {
        "name": "Hoàng Thị Thu Hằng",
        "id": "100015263801555"
    },
    {
        "name": "Ngoc Pham",
        "id": "100015271773451"
    },
    {
        "name": "Lưu Phụng Ái",
        "id": "100015776442365"
    },
    {
        "name": "Sang Nguyễn",
        "id": "100015873420347"
    },
    {
        "name": "Karen Helene",
        "id": "100015930346594"
    },
    {
        "name": "Trần Hội",
        "id": "100016153863646"
    },
    {
        "name": "BT.Tran Quyến",
        "id": "100016437768953"
    },
    {
        "name": "Ngáo Ngơ",
        "id": "100016891818661"
    },
    {
        "name": "Tao Nho Xa May",
        "id": "100017000194070"
    },
    {
        "name": "Phước Hiền",
        "id": "100017593759064"
    },
    {
        "name": "Tran Thi Minh Tiên",
        "id": "100018575868502"
    },
    {
        "name": "Huỳnh Văn Luân",
        "id": "100020158567285"
    },
    {
        "name": "Hieu Nguyen",
        "id": "100020770548959"
    },
    {
        "name": "Vuong Cuong",
        "id": "100020992309635"
    },
    {
        "name": "Binh Luong",
        "id": "100021471380506"
    },
    {
        "name": "Lâm Tran",
        "id": "100021841748737"
    },
    {
        "name": "Hao Chi",
        "id": "100021927465641"
    },
    {
        "name": "Nhung Nguyen",
        "id": "100023025828494"
    },
    {
        "name": "Dũng Đinh",
        "id": "100023065901614"
    },
    {
        "name": "Nhàn Nguyễn",
        "id": "100023593680442"
    },
    {
        "name": "Tâm Nguyen",
        "id": "100023653943042"
    },
    {
        "name": "Huỳnh Hoàng Huy",
        "id": "100023694377094"
    },
    {
        "name": "Nuong Le",
        "id": "100024162165083"
    },
    {
        "name": "Như Ý Lê",
        "id": "100024323168473"
    },
    {
        "name": "Mrhuy Thắng",
        "id": "100024491371504"
    },
    {
        "name": "Nguyen Dinh Minh",
        "id": "100024849996183"
    },
    {
        "name": "Hoà Trần",
        "id": "100024920461365"
    },
    {
        "name": "Minh Tú",
        "id": "100024927736003"
    },
    {
        "name": "Minh Liem",
        "id": "100025239771649"
    },
    {
        "name": "Hoàng Ngọc Bảo Khoa",
        "id": "100025311369923"
    },
    {
        "name": "Vũ Đình Triều",
        "id": "100025391437985"
    },
    {
        "name": "Phong Le Hong",
        "id": "100025918943427"
    },
    {
        "name": "Phạm Thư",
        "id": "100025920698056"
    },
    {
        "name": "Nguyễn Long Thịnh",
        "id": "100026144328967"
    },
    {
        "name": "トゥアン アイン",
        "id": "100026336092213"
    },
    {
        "name": "Tuan Luu",
        "id": "100026441766560"
    },
    {
        "name": "Giàng A Pèng",
        "id": "100026518667606"
    },
    {
        "name": "Mi Nguyen",
        "id": "100027171893602"
    },
    {
        "name": "An Nguyen",
        "id": "100027323897713"
    },
    {
        "name": "Huynh Cuong",
        "id": "100027422468700"
    },
    {
        "name": "Nhat Le",
        "id": "100027505990834"
    },
    {
        "name": "Xuan Khanh",
        "id": "100027624154561"
    },
    {
        "name": "Thanh Tuấn",
        "id": "100028061269866"
    },
    {
        "name": "Nguen Nhi",
        "id": "100028146402832"
    },
    {
        "name": "Nguyễn Hoàng Phúc",
        "id": "100028226302738"
    },
    {
        "name": "Đặng Kiều",
        "id": "100028662172257"
    },
    {
        "name": "Tuyết Hồng",
        "id": "100028827013677"
    },
    {
        "name": "Khải Phan",
        "id": "100029083008542"
    },
    {
        "name": "Tí Nguyễn",
        "id": "100030034470840"
    },
    {
        "name": "Mi Doan",
        "id": "100030185623508"
    },
    {
        "name": "Hiếu Trung Lê",
        "id": "100030538420180"
    },
    {
        "name": "Như Quỳnh",
        "id": "100030660880942"
    },
    {
        "name": "Trân My",
        "id": "100031067110890"
    },
    {
        "name": "Hoa Tím Nặng Tình",
        "id": "100031489596610"
    },
    {
        "name": "Han Co Don",
        "id": "100032761792090"
    },
    {
        "name": "Phuongdung Tranle",
        "id": "100033427897658"
    },
    {
        "name": "Tuấn Nghĩa",
        "id": "100033827629068"
    },
    {
        "name": "Long Minh",
        "id": "100034280920735"
    },
    {
        "name": "Quoc Huy",
        "id": "100034590245582"
    },
    {
        "name": "Tan Tan",
        "id": "100035123821227"
    },
    {
        "name": "Tùng Heo",
        "id": "100035245714353"
    },
    {
        "name": "Huy Cao",
        "id": "100035275632107"
    },
    {
        "name": "Hoàng Minh",
        "id": "100035308265354"
    },
    {
        "name": "Thu Thao",
        "id": "100035422118188"
    },
    {
        "name": "Khương Lê",
        "id": "100035423281949"
    },
    {
        "name": "Nguyễn Lĩnh",
        "id": "100035726537363"
    },
    {
        "name": "Nhieu Romeo",
        "id": "100035759704933"
    },
    {
        "name": "Phú Trung",
        "id": "100035794802527"
    },
    {
        "name": "Nam Hai",
        "id": "100036130503277"
    },
    {
        "name": "Võ Thị Thủy Tiên",
        "id": "100036566470240"
    },
    {
        "name": "Quy Tran Duy",
        "id": "100037018938530"
    },
    {
        "name": "Minh Vương",
        "id": "100037635137201"
    },
    {
        "name": "Thu An",
        "id": "100037647312188"
    },
    {
        "name": "Trang Thanh",
        "id": "100037692226399"
    },
    {
        "name": "La Vang Oi",
        "id": "100038127125970"
    },
    {
        "name": "Đặng Văn Khanh",
        "id": "100038325391774"
    },
    {
        "name": "Ý Thanh Nguyen",
        "id": "100038885940950"
    },
    {
        "name": "Nguyễn Quốc Khánh",
        "id": "100038934184299"
    },
    {
        "name": "Bảo Chì",
        "id": "100039251026128"
    },
    {
        "name": "Nguyễn Văn Quí Quí",
        "id": "100039487929662"
    },
    {
        "name": "An Bình Nguyễn",
        "id": "100039546288383"
    },
    {
        "name": "Linh Thảo Nhân Nghĩa",
        "id": "100040218180448"
    },
    {
        "name": "Kim Duyên",
        "id": "100040659396285"
    },
    {
        "name": "Thắng TN",
        "id": "100041625366410"
    },
    {
        "name": "Đoàn Minh",
        "id": "100041645491382"
    },
    {
        "name": "Vỏ Hà Hiển",
        "id": "100041652908269"
    },
    {
        "name": "Hồng Hương",
        "id": "100044221840753"
    },
    {
        "name": "Hoàng X Hoà",
        "id": "100044359865862"
    },
    {
        "name": "Chí Linh",
        "id": "100046415556546"
    },
    {
        "name": "Linh Linh",
        "id": "100046580604020"
    },
    {
        "name": "Nku Y Pkam",
        "id": "100047898342499"
    },
    {
        "name": "Ngô Viên",
        "id": "100049557552952"
    },
    {
        "name": "Xuân Mừng",
        "id": "100049620007179"
    },
    {
        "name": "Uc Umi",
        "id": "100049860811370"
    },
    {
        "name": "Sang Nguyen",
        "id": "100050224726123"
    },
    {
        "name": "Hồng Phúc",
        "id": "100050551384594"
    },
    {
        "name": "Thang Nguyen",
        "id": "100050691069265"
    },
    {
        "name": "Lê Tuấn Khanh",
        "id": "100050710730998"
    },
    {
        "name": "Huy Dubaii",
        "id": "100051914386616"
    },
    {
        "name": "Kiều Oanh",
        "id": "100051954713025"
    },
    {
        "name": "Quoc Khanh Dang",
        "id": "100052415628758"
    },
    {
        "name": "Nguyen Yeu",
        "id": "100052470472742"
    },
    {
        "name": "MinhPhuc Bùi",
        "id": "100052656727317"
    },
    {
        "name": "Quynh Anh",
        "id": "100052799332977"
    },
    {
        "name": "Dat Nguyen",
        "id": "100052843971039"
    },
    {
        "name": "Mai Hoa",
        "id": "100053021861801"
    },
    {
        "name": "Hoàng Văn Tuyền",
        "id": "100053132190762"
    },
    {
        "name": "Quế Chi",
        "id": "100053194202833"
    },
    {
        "name": "Thanh Hải",
        "id": "100053238090277"
    }
]